hahahellooo_cmd/__init__.py
hahahellooo_cmd/cmd.py
hahahellooo_cmd-0.1.0.dist-info/METADATA
hahahellooo_cmd-0.1.0.dist-info/WHEEL
hahahellooo_cmd-0.1.0.dist-info/entry_points.txt
hahahellooo_cmd-0.1.0.dist-info/top_level.txt
hahahellooo_cmd-0.1.0.dist-info/RECORD
